<?xml version="1.0" encoding="windows-1251"?>
<string_table>
	<string id="task_atp_propusk_0">
		<rus>Миниган</rus>
		<eng>Миниган</eng>
		<ukr>Мініган</ukr>
	</string>
	<string id="task_atp_propusk_1">
		<rus>Найти миниган</rus>
		<eng>Найти миниган</eng>
		<ukr>Знайти мініган</ukr>
	</string>
	<string id="task_atp_propusk_2">
		<rus>Принести миниган Адреналину</rus>
		<eng>Принести миниган Адреналину</eng>
		<ukr>Принести мініган Адреналіну</ukr>
	</string>
	<string id="task_baty_zadan_0">
		<rus>Звуковой сигнал</rus>
		<eng>Звуковой сигнал</eng>
		<ukr>Звуковий сигнал</ukr>
	</string>
	<string id="task_baty_zadan_1">
		<rus>Найти предмет, издающий шум</rus>
		<eng>Найти предмет, издающий шум</eng>
		<ukr>Знайти предмет, що шумить</ukr>
	</string>
	<string id="task_baty_zadan_2">
		<rus>Принести найденное Сахарову</rus>
		<eng>Принести найденное Сахарову</eng>
		<ukr>Принести знайдене Сахарову</ukr>
	</string>
	<string id="task_arhara_ekza_0">
		<rus>Маскировочный экзоскелет</rus>
		<eng>Маскировочный экзоскелет</eng>
		<ukr>Маскувальний екзоскелет</ukr>
	</string>
	<string id="task_arhara_ekza_1">
		<rus>Найти маскировочный экзоскелет</rus>
		<eng>Найти маскировочный экзоскелет</eng>
		<ukr>Знайти маскувальний екзоскелет</ukr>
	</string>
	<string id="task_arhara_ekza_2">
		<rus>Принести экзоскелет Воронину</rus>
		<eng>Принести экзоскелет Воронину</eng>
		<ukr>Принести екзоскелет Вороніну</ukr>
	</string>
	<string id="task_atp_shurup_propusk_0">
		<rus>Разведка боем</rus>
		<eng>Разведка боем</eng>
		<ukr>Розвідка боєм</ukr>
	</string>
	<string id="task_atp_shurup_propusk_1">
		<rus>Узнать подробности активности наёмников у Фаната</rus>
		<eng>Узнать подробности активности наёмников у Фаната</eng>
		<ukr>Довідатися подробиці активності найманців у Фаната</ukr>
	</string>
	<string id="task_atp_shurup_propusk_2">
		<rus>Разведать обстановку на Заводе и по возможности найти тиски</rus>
		<eng>Разведать обстановку на Заводе и по возможности найти тиски</eng>
		<ukr>Розвідати обстановку на Заводі і по можливості знайти лещата</ukr>
	</string>
	<string id="task_atp_shurup_propusk_3">
		<rus>Принести найденные ПДА и тиски Шурупу</rus>
		<eng>Принести найденные ПДА и тиски Шурупу</eng>
		<ukr>Принести знайдені КПК і лещата Шурупу</ukr>
	</string>
	<string id="task_ugrum_plaer_0">
		<rus>Хорошая сделка</rus>
		<eng>Хорошая сделка</eng>
		<ukr>Хороша угода</ukr>
	</string>
	<string id="task_ugrum_plaer_1">
		<rus>Найти антизомбин для часового</rus>
		<eng>Найти антизомбин для часового</eng>
		<ukr>Знайти антизомбин для вартового</ukr>
	</string>
	<string id="task_ugrum_plaer_2">
		<rus>Поговорить с главным часовым</rus>
		<eng>Поговорить с главным часовым</eng>
		<ukr>Поговорити с головним вартовим</ukr>
	</string>
	<string id="task_atp_mozg_0">
		<rus>Мозги контролёра</rus>
		<eng>Мозги контролёра</eng>
		<ukr>Мізки контролера</ukr>
	</string>
	<string id="task_atp_mozg_1">
		<rus>Найти два мозга контролёра</rus>
		<eng>Найти два мозга контролёра</eng>
		<ukr>Знайти два мозки контролера</ukr>
	</string>
	<string id="task_atp_mozg_2">
		<rus>Отнести мозги контролёра Лукашу</rus>
		<eng>Отнести мозги контролёра Лукашу</eng>
		<ukr>Віднести мозки контролера Лукашу</ukr>
	</string>
	<string id="task_adrenalin_disk_0">
		<rus>Диск для Адреналина</rus>
		<eng>Диск для Адреналина</eng>
		<ukr>Диск для Адреналіна</ukr>
	</string>
	<string id="task_adrenalin_disk_1">
		<rus>Найти компьютерный диск</rus>
		<eng>Найти компьютерный диск</eng>
		<ukr>Знайти комп'ютерний диск</ukr>
	</string>
	<string id="task_adrenalin_disk_2">
		<rus>Принести диск Адреналину</rus>
		<eng>Принести диск Адреналину</eng>
		<ukr>Принести диск Адреналіну</ukr>
	</string>
	<string id="task_sahar_sumka_0">
		<rus>Медсумка Сахарова</rus>
		<eng>Медсумка Сахарова</eng>
		<ukr>Медсумка Сахарова</ukr>
	</string>
	<string id="task_sahar_sumka_1">
		<rus>Найти медсумку на ЧАЭС-1</rus>
		<eng>Найти медсумку на ЧАЭС-1</eng>
		<ukr>Знайти медсумку на ЧАЕС-1</ukr>
	</string>
	<string id="task_sahar_sumka_2">
		<rus>Принести медсумку Сахарову</rus>
		<eng>Принести медсумку Сахарову</eng>
		<ukr>Принести медсумку Сахарову</ukr>
	</string>
	<string id="task_arhara_doctor_0">
		<rus>Медальон Доктора</rus>
		<eng>Медальон Доктора</eng>
		<ukr>Медальйон Доктора</ukr>
	</string>
	<string id="task_arhara_doctor_1">
		<rus>Найти медальон</rus>
		<eng>Найти медальон</eng>
		<ukr>Знайти медальйон</ukr>
	</string>
	<string id="task_arhara_doctor_2">
		<rus>Принести медальон Доктору</rus>
		<eng>Принести медальон Доктору</eng>
		<ukr>Принести медальйон Доктору</ukr>
	</string>
	<string id="task_vorona_povar_0">
		<rus>Вороньи яйца</rus>
		<eng>Вороньи яйца</eng>
		<ukr>Воронячі яйця</ukr>
	</string>
	<string id="task_vorona_povar_1">
		<rus>Найти вороньи яйца в Забытом Лесу</rus>
		<eng>Найти вороньи яйца в Забытом Лесу</eng>
		<ukr>Знайти воронячі яйця у Забутому Лісі</ukr>
	</string>
	<string id="task_vorona_povar_2">
		<rus>Принести вороньи яйца Повару</rus>
		<eng>Принести вороньи яйца Повару</eng>
		<ukr>Принести воронячі яйця Кухарю</ukr>
	</string>
	<string id="task_lekarstvo_bandita_nayti_0">
		<rus>Лекарство для Акима</rus>
		<eng>Лекарство для Акима</eng>
		<ukr>Ліки для Акима</ukr>
	</string>
	<string id="task_lekarstvo_bandita_nayti_1">
		<rus>Найти лекарство на блокпосту</rus>
		<eng>Найти лекарство на блокпосту</eng>
		<ukr>Знайти ліки на блокпосту</ukr>
	</string>
	<string id="task_lekarstvo_bandita_nayti_2">
		<rus>Принести лекарство Акиму</rus>
		<eng>Принести лекарство Акиму</eng>
		<ukr>Принести ліки Акиму</ukr>
	</string>
	<string id="task_shaxter_fonar_0">
		<rus>Фонарики для Шахтёра</rus>
		<eng>Фонарики для Шахтёра</eng>
		<ukr>Ліхтарики для Шахтара</ukr>
	</string>
	<string id="task_shaxter_fonar_1">
		<rus>Найти два фонарика</rus>
		<eng>Найти два фонарика</eng>
		<ukr>Знайти 2 ліхтарика</ukr>
	</string>
	<string id="task_shaxter_fonar_2">
		<rus>Принести фонарики Шахтёру</rus>
		<eng>Принести фонарики Шахтёру</eng>
		<ukr>Принести ліхтарики Шахтару</ukr>
	</string>
	<string id="task_akim_kubik_rubik_0">
		<rus>Кубик Рубика</rus>
		<eng>Кубик Рубика</eng>
		<ukr>Кубик Рубіка</ukr>
	</string>
	<string id="task_akim_kubik_rubik_1">
		<rus>Найти кубик в Тёмной Долине</rus>
		<eng>Найти кубик в Тёмной Долине</eng>
		<ukr>Знайти кубик у Темній Долині</ukr>
	</string>
	<string id="task_akim_kubik_rubik_2">
		<rus>Принести найденное Акиму</rus>
		<eng>Принести найденное Акиму</eng>
		<ukr>Принести кубік Акиму</ukr>
	</string>
	<string id="task_shaxter_kniga_0">
		<rus>Книга Шахтёра</rus>
		<eng>Книга Шахтёра</eng>
		<ukr>Книга Шахтара</ukr>
	</string>
	<string id="task_shaxter_kniga_1">
		<rus>Найти книгу в Забытом Лесу</rus>
		<eng>Найти книгу в Забытом Лесу</eng>
		<ukr>Знайти книгу у Забутому Лісі</ukr>
	</string>
	<string id="task_shaxter_kniga_2">
		<rus>Принести книгу Шахтёру</rus>
		<eng>Принести книгу Шахтёру</eng>
		<ukr>Принести книгу Шахтару</ukr>
	</string>
	<string id="task_lysyi_klad_0">
		<rus>Поиски клада: Пещера</rus>
		<eng>Поиски клада: Пещера</eng>
		<ukr>Пошуки скарбу: Печера</ukr>
	</string>
	<string id="task_lysyi_klad_1">
		<rus>Найти клад в Пещере</rus>
		<eng>Найти клад в Пещере</eng>
		<ukr>Знайти скарб у Печері</ukr>
	</string>
	<string id="task_lysyi_klad_2">
		<rus>Принести клад Лысому</rus>
		<eng>Принести клад Лысому</eng>
		<ukr>Принести скарб Лисому</ukr>
	</string>
	<string id="task_pda_sh_strelok_0">
		<rus>"Скальп контролёра"</rus>
		<eng>"Скальп контролёра"</eng>
		<ukr>"Скальп контролера"</ukr>
	</string>
	<string id="task_pda_sh_strelok_1">
		<rus>Найти "Скальп контролёра"</rus>
		<eng>Найти "Скальп контролёра"</eng>
		<ukr>Знайти "Скальп контролера"</ukr>
	</string>
	<string id="task_pda_sh_strelok_2">
		<rus>Принести артефакт Шахтёру</rus>
		<eng>Принести артефакт Шахтёру</eng>
		<ukr>Принести артефакт Шахтару</ukr>
	</string>
	<string id="task_petrenko_flyga_0">
		<rus>Фляжка Петренко</rus>
		<eng>Фляжка Петренко</eng>
		<ukr>Фляжка Петренко</ukr>
	</string>
	<string id="task_petrenko_flyga_1">
		<rus>Найти фляжку</rus>
		<eng>Найти фляжку</eng>
		<ukr>Знайти фляжку</ukr>
	</string>
	<string id="task_petrenko_flyga_2">
		<rus>Принести фляжку полковнику</rus>
		<eng>Принести фляжку полковнику</eng>
		<ukr>Принести фляжку полковнику</ukr>
	</string>
	<string id="task_dolgovyzui_0">
		<rus>Микросхемы</rus>
		<eng>Микросхемы</eng>
		<ukr>Мікросхеми</ukr>
	</string>
	<string id="task_dolgovyzui_1">
		<rus>Найти микросхемы на Кордоне</rus>
		<eng>Найти микросхемы на Кордоне</eng>
		<ukr>Знайти мікросхеми на Кордоні</ukr>
	</string>
	<string id="task_dolgovyzui_2">
		<rus>Принести микросхемы Долговязому</rus>
		<eng>Принести микросхемы Долговязому</eng>
		<ukr>Принести мікросхеми Довгов'язому.</ukr>
	</string>
	<string id="task_voronin_termos_0">
		<rus>Термосы для Воронина</rus>
		<eng>Термосы для Воронина</eng>
		<ukr>Термоси для Вороніна</ukr>
	</string>
	<string id="task_voronin_termos_1">
		<rus>Найти термосы в Зоне</rus>
		<eng>Найти термосы в Зоне</eng>
		<ukr>Знайти термоси в Зоні</ukr>
	</string>
	<string id="task_voronin_termos_2">
		<rus>Принести термосы Воронину</rus>
		<eng>Принести термосы Воронину</eng>
		<ukr>Принести термоси Вороніну</ukr>
	</string>
	<string id="task_garik_vop_0">
		<rus>Сигареты для Гарика</rus>
		<eng>Сигареты для Гарика</eng>
		<ukr>Сигарети для Гарика</ukr>
	</string>
	<string id="task_garik_vop_1">
		<rus>Найти сигареты</rus>
		<eng>Найти сигареты</eng>
		<ukr>Знайти сигарети</ukr>
	</string>
	<string id="task_garik_vop_2">
		<rus>Принести сигареты и деньги</rus>
		<eng>Принести сигареты и деньги</eng>
		<ukr>Принести сигарети і гроші</ukr>
	</string>
	<string id="task_petr_sidor_0">
		<rus>Ремкомплекты</rus>
		<eng>Ремкомплекты</eng>
		<ukr>Ремкомплекти</ukr>
	</string>
	<string id="task_petr_sidor_1">
		<rus>Найти ремкомплекты</rus>
		<eng>Найти ремкомплекты</eng>
		<ukr>Знайти ремкомплекти</ukr>
	</string>
	<string id="task_petr_sidor_2">
		<rus>Принести ремкомплекты Сидоровичу</rus>
		<eng>Принести ремкомплекты Сидоровичу</eng>
		<ukr>Принести ремкомплекти Сидоровичу</ukr>
	</string>
	<string id="task_voronin_stol_0">
		<rus>Компьютер и видеорация</rus>
		<eng>Компьютер и видеорация</eng>
		<ukr>Комп'ютер і відеорація</ukr>
	</string>
	<string id="task_voronin_stol_1">
		<rus>Найти компьютер</rus>
		<eng>Найти компьютер</eng>
		<ukr>Знайти комп'ютер</ukr>
	</string>
	<string id="task_voronin_stol_2">
		<rus>Разыскать видеорацию</rus>
		<eng>Разыскать видеорацию</eng>
		<ukr>Розшукати відеорацію</ukr>
	</string>
	<string id="task_voronin_stol_3">
		<rus>Принести найденное генералу</rus>
		<eng>Принести найденное генералу</eng>
		<ukr>Принести знайдене генералу</ukr>
	</string>
	<string id="task_sahar_ekolog_0">
		<rus>Встреча с экологами</rus>
		<eng>Встреча с экологами</eng>
		<ukr>Зустріти з екологам</ukr>
	</string>
	<string id="task_sahar_ekolog_1">
		<rus>Встретить экологов</rus>
		<eng>Встретить экологов</eng>
		<ukr>Зустріти екологів</ukr>
	</string>
	<string id="task_sahar_ekolog_2">
		<rus>Забрать рацию у экологов</rus>
		<eng>Забрать рацию у экологов</eng>
		<ukr>Забрати рацію у екологів</ukr>
	</string>
	<string id="task_sahar_ekolog_3">
		<rus>Принести рацию Сахарову</rus>
		<eng>Принести рацию Сахарову</eng>
		<ukr>Принести рацію Сахарову</ukr>
	</string>
	<string id="task_voronin_infa_0">
		<rus>Решительные меры</rus>
		<eng>Решительные меры</eng>
		<ukr>Рішучі заходи</ukr>
	</string>
	<string id="task_voronin_infa_1">
		<rus>Раздобыть ОЦ-14 «Гроза»</rus>
		<eng>Раздобыть ОЦ-14 «Гроза»</eng>
		<ukr>Роздобути ОЦ-14 «Гроза»</ukr>
	</string>
	<string id="task_voronin_infa_2">
		<rus>Доложить Воронину</rus>
		<eng>Доложить Воронину</eng>
		<ukr>Доповісти Вороніну</ukr>
	</string>
	<string id="task_naemn_shturm_0">
		<rus>Оборона Бара</rus>
		<eng>Оборона Бара</eng>
		<ukr>Оборона Бару</ukr>
	</string>
	<string id="task_naemn_shturm_1">
		<rus>Помочь долговцам удержать Бар и убить Горба</rus>
		<eng>Помочь долговцам удержать Бар и убить Горба</eng>
		<ukr>Допомогти долгівцям утримати Бар і вбити Горба</ukr>
	</string>
	<string id="task_naemn_shturm_2">
		<rus>Доложить Воронину</rus>
		<eng>Доложить Воронину</eng>
		<ukr>Доповісти Вороніну</ukr>
	</string>
	<string id="task_kalinin_atp_0">
		<rus>Ликвидация</rus>
		<eng>Ликвидация</eng>
		<ukr>Ліквідація</ukr>
	</string>
	<string id="task_kalinin_atp_1">
		<rus>Отбить атаку бандитов и убить Шныру</rus>
		<eng>Отбить атаку бандитов и убить Шныру</eng>
		<ukr>Відбити атаку бандитів і вбити Шниру</ukr>
	</string>
	<string id="task_kalinin_atp_2">
		<rus>Доложить Калинину</rus>
		<eng>Доложить Калинину</eng>
		<ukr>Доповісти Калиніну</ukr>
	</string>
	<string id="task_gonets_atp_0">
		<rus>Встреча с гонцом</rus>
		<eng>Встреча с гонцом</eng>
		<ukr>Зустріч з гінцем</ukr>
	</string>
	<string id="task_gonets_atp_1">
		<rus>Забрать информацию у гонца</rus>
		<eng>Забрать информацию у гонца</eng>
		<ukr>Забрати інформацію у гінця</ukr>
	</string>
	<string id="task_gonets_atp_2">
		<rus>Принести флешку Калинину</rus>
		<eng>Принести флешку Калинину</eng>
		<ukr>Принести флешку Калиніну</ukr>
	</string>
	<string id="task_kalinin_btr_0">
		<rus>В осаде</rus>
		<eng>В осаде</eng>
		<ukr>В облозі</ukr>
	</string>
	<string id="task_kalinin_btr_1">
		<rus>Раздобыть гранатомёт РПГ-7 и заряды</rus>
		<eng>Раздобыть гранатомёт РПГ-7 и заряды</eng>
		<ukr>Роздобути гранатомет РПГ-7 і заряди</ukr>
	</string>
	<string id="task_kalinin_btr_2">
		<rus>Доложить Калинину</rus>
		<eng>Доложить Калинину</eng>
		<ukr>Доповісти Калиніну</ukr>
	</string>
	<string id="task_btr_ataka_0">
		<rus>Противостояние</rus>
		<eng>Противостояние</eng>
		<ukr>Протистояння</ukr>
	</string>
	<string id="task_btr_ataka_1">
		<rus>Убить командира спецназа</rus>
		<eng>Убить командира спецназа</eng>
		<ukr>Вбить командира спецназу</ukr>
	</string>
	<string id="task_btr_ataka_2">
		<rus>Уничтожить первый БТР</rus>
		<eng>Уничтожить первый БТР</eng>
		<ukr>Знищити перший БТР</ukr>
	</string>
	<string id="task_btr_ataka_3">
		<rus>Уничтожить второй БТР</rus>
		<eng>Уничтожить второй БТР</eng>
		<ukr>Знищити другий БТР</ukr>
	</string>
	<string id="task_btr_ataka_4">
		<rus>Уничтожить третий БТР</rus>
		<eng>Уничтожить третий БТР</eng>
		<ukr>Знищити третій БТР</ukr>
	</string>
	<string id="task_btr_ataka_5">
		<rus>Доложить Калинину</rus>
		<eng>Доложить Калинину</eng>
		<ukr>Доповісти Калиніну</ukr>
	</string>
	<string id="task_shax_plennik_0">
		<rus>Кодовый замок</rus>
		<eng>Кодовый замок</eng>
		<ukr>Кодовий замок</ukr>
	</string>
	<string id="task_shax_plennik_1">
		<rus>Освободить пленника</rus>
		<eng>Освободить пленника</eng>
		<ukr>Звільнити полоненого</ukr>
	</string>
	<string id="task_shax_plennik_2">
		<rus>Вернуться к Шахтёру</rus>
		<eng>Вернуться к Шахтёру</eng>
		<ukr>Повернутися до Шахтара</ukr>
	</string>
	<string id="task_fima_mulo_0">
		<rus>Мыло для Фимы</rus>
		<eng>Мыло для Фимы</eng>
		<ukr>Мило для Фими</ukr>
	</string>
	<string id="task_fima_mulo_1">
		<rus>Достать мыло с помощью импульсных гранат</rus>
		<eng>Достать мыло с помощью импульсных гранат</eng>
		<ukr>Дістати мило за допомогою імпульсних гранат</ukr>
	</string>
	<string id="task_fima_mulo_2">
		<rus>Принести мыло Фиме</rus>
		<eng>Принести мыло Фиме</eng>
		<ukr>Принести мило Фимі</ukr>
	</string>
	<string id="task_adr_shkatulka_0">
		<rus>Шкатулка и сейф</rus>
		<eng>Шкатулка и сейф</eng>
		<ukr>Скринька і сейф</ukr>
	</string>
	<string id="task_adr_shkatulka_1">
		<rus>Взять необходимое</rus>
		<eng>Взять необходимое</eng>
		<ukr>Взяти необхідне</ukr>
	</string>
	<string id="task_adr_shkatulka_2">
		<rus>Принести шкатулку Адреналину</rus>
		<eng>Принести шкатулку Адреналину</eng>
		<ukr>Принести скриньку Адреналіну</ukr>
	</string>
	<string id="task_tretiy_kod_0">
		<rus>Кодовый замок</rus>
		<eng>Кодовый замок</eng>
		<ukr>Кодовий замок</ukr>
	</string>
	<string id="task_tretiy_kod_1">
		<rus>Взять сейф</rus>
		<eng>Взять сейф</eng>
		<ukr>Взяти сейф</ukr>
	</string>
	<string id="task_tretiy_kod_2">
		<rus>Принести сейф Шахтёру</rus>
		<eng>Принести сейф Шахтёру</eng>
		<ukr>Принести сейф Шахтару</ukr>
	</string>
	<string id="task_sidor_amulet_0">
		<rus>Ремонтные ящики</rus>
		<eng>Ремонтные ящики</eng>
		<ukr>Ремонтні ящики</ukr>
	</string>
	<string id="task_sidor_amulet_1">
		<rus>Найти ремонтные ящики</rus>
		<eng>Найти ремонтные ящики</eng>
		<ukr>Взяти ремонтні ящики</ukr>
	</string>
	<string id="task_sidor_amulet_2">
		<rus>Принести заказ торговцу</rus>
		<eng>Принести заказ торговцу</eng>
		<ukr>Принести замовлення торговцю</ukr>
	</string>
	<string id="task_otshelnik_yzik_0">
		<rus>Ящик с оружием</rus>
		<eng>Ящик с оружием</eng>
		<ukr>Ящик зі зброєю</ukr>
	</string>
	<string id="task_otshelnik_yzik_1">
		<rus>Найти ящик с оружием</rus>
		<eng>Найти ящик с оружием</eng>
		<ukr>Взяти ящик зі зброєю</ukr>
	</string>
	<string id="task_otshelnik_yzik_2">
		<rus>Отнести ящик Отшельнику</rus>
		<eng>Отнести ящик Отшельнику</eng>
		<ukr>Принести ящик Самітнику</ukr>
	</string>
	<string id="task_ginekolog_lekarstvo_0">
		<rus>Лекарства для Гинеколога</rus>
		<eng>Лекарства для Гинеколога</eng>
		<ukr>Ліки для Гінеколога</ukr>
	</string>
	<string id="task_ginekolog_lekarstvo_1">
		<rus>Найти лекарства</rus>
		<eng>Найти лекарства</eng>
		<ukr>Взяти ліки</ukr>
	</string>
	<string id="task_ginekolog_lekarstvo_2">
		<rus>Принести заказ Гинекологу</rus>
		<eng>Принести заказ Гинекологу</eng>
		<ukr>Принести замовлення Гінекологу</ukr>
	</string>
	<string id="task_jora_accumul_seif_0">
		<rus>Аккумуляторы</rus>
		<eng>Аккумуляторы</eng>
		<ukr>Акумулятори</ukr>
	</string>
	<string id="task_jora_accumul_seif_1">
		<rus>Найти аккумуляторы</rus>
		<eng>Найти аккумуляторы</eng>
		<ukr>Знайти акумулятори</ukr>
	</string>
	<string id="task_jora_accumul_seif_2">
		<rus>Принести заказ Жорику</rus>
		<eng>Принести заказ Жорику</eng>
		<ukr>Принести замовлення Жорику</ukr>
	</string>
	<string id="task_starik_zadanie_0">
		<rus>Часы Старика</rus>
		<eng>Часы Старика</eng>
		<ukr>Годинник Старого</ukr>
	</string>
	<string id="task_starik_zadanie_1">
		<rus>Найти часы</rus>
		<eng>Найти часы</eng>
		<ukr>Знайти годинник</ukr>
	</string>
	<string id="task_starik_zadanie_2">
		<rus>Принести часы Старику</rus>
		<eng>Принести часы Старику</eng>
		<ukr>Принести годинник Старому</ukr>
	</string>
	<string id="task_piligrim_britva_0">
		<rus>Схрон Пилигрима</rus>
		<eng>Схрон Пилигрима</eng>
		<ukr>Схрон Пілігрима</ukr>
	</string>
	<string id="task_piligrim_britva_1">
		<rus>Найти схрон Пилигрима</rus>
		<eng>Найти схрон Пилигрима</eng>
		<ukr>Знайти схрон Пілігрима</ukr>
	</string>
	<string id="task_piligrim_britva_2">
		<rus>Принести обещанное Пилигриму</rus>
		<eng>Принести обещанное Пилигриму</eng>
		<ukr>Принести обіцяне Пілігриму</ukr>
	</string>
	<string id="task_otsh_pda_0">
		<rus>Ультрадетектор</rus>
		<eng>Ультрадетектор</eng>
		<ukr>Ультрадетектор</ukr>
	</string>
	<string id="task_otsh_pda_1">
		<rus>Достать ультрадетектор</rus>
		<eng>Достать ультрадетектор</eng>
		<ukr>Дістати ультрадетектор</ukr>
	</string>
	<string id="task_otsh_pda_2">
		<rus>Принести детектор Адреналину</rus>
		<eng>Принести детектор Адреналину</eng>
		<ukr>Принести детектор Адреналіну</ukr>
	</string>
	<string id="task_golo_detektor_0">
		<rus>Сборка детектора</rus>
		<eng>Сборка детектора</eng>
		<ukr>Збір детектора</ukr>
	</string>
	<string id="task_golo_detektor_1">
		<rus>Найти элитные детекторы</rus>
		<eng>Найти элитные детекторы</eng>
		<ukr>Дістати елітні детектори</ukr>
	</string>
	<string id="task_golo_detektor_2">
		<rus>Принести детекторы Голограмме</rus>
		<eng>Принести детекторы Голограмме</eng>
		<ukr>Принести детектори Голограмі</ukr>
	</string>
	<string id="task_medik_pribor_1_0">
		<rus>Поиск дискеты</rus>
		<eng>Поиск дискеты</eng>
		<ukr>Пошук дискети</ukr>
	</string>
	<string id="task_medik_pribor_1_1">
		<rus>Найти дискету</rus>
		<eng>Найти дискету</eng>
		<ukr>Знайти дискету</ukr>
	</string>
	<string id="task_medik_pribor_1_2">
		<rus>Принести дискету Гинекологу</rus>
		<eng>Принести дискету Гинекологу</eng>
		<ukr>Принести дискету Гінекологу</ukr>
	</string>
	<string id="task_akkum_and_mikposx_0">
		<rus>Блоки питания</rus>
		<eng>Блоки питания</eng>
		<ukr>Блоки живлення</ukr>
	</string>
	<string id="task_akkum_and_mikposx_1">
		<rus>Найти блоки питания и плату</rus>
		<eng>Найти блоки питания и плату</eng>
		<ukr>Знайти блоки живлення і плату</ukr>
	</string>
	<string id="task_akkum_and_mikposx_2">
		<rus>Принести заказ Шуре</rus>
		<eng>Принести заказ Шуре</eng>
		<ukr>Принести замовлення Сашку</ukr>
	</string>
	<string id="task_chimaera_zadan_0">
		<rus>Убийство Сидоровича</rus>
		<eng>Убийство Сидоровича</eng>
		<ukr>Вбивство Сидоровича</ukr>
	</string>
	<string id="task_chimaera_zadan_1">
		<rus>Убить Сидоровича</rus>
		<eng>Убить Сидоровича</eng>
		<ukr>Вбити Сидора</ukr>
	</string>
	<string id="task_chimaera_zadan_2">
		<rus>Принести голову Сидоровича</rus>
		<eng>Принести голову Сидоровича</eng>
		<ukr>Принести голову Сидоровича</ukr>
	</string>
	<string id="task_land_oxot_0">
		<rus>Чучело</rus>
		<eng>Чучело</eng>
		<ukr>Опудало</ukr>
	</string>
	<string id="task_land_oxot_1">
		<rus>Убить матёрого контролёра на стадионе Припяти, не задев голову мутанта</rus>
		<eng>Убить матёрого контролёра на стадионе Припяти, не задев голову мутанта</eng>
		<ukr>Вбить зрілого контролера на стадіоні Прип'яті, не зачепивши голову мутанта</ukr>
	</string>
	<string id="task_land_oxot_2">
		<rus>Забрать труп контролёра</rus>
		<eng>Забрать труп контролёра</eng>
		<ukr>Забрати труп контролера</ukr>
	</string>
	<string id="task_land_oxot_3">
		<rus>Отнести тело мутанта Филину</rus>
		<eng>Отнести тело мутанта Филину</eng>
		<ukr>Віднести тіло мутанта Філін</ukr>
	</string>
	<string id="task_ginek_vlip_0">
		<rus>Колбы для Гинеколога</rus>
		<eng>Колбы для Гинеколога</eng>
		<ukr>Колби для Гінеколога</ukr>
	</string>
	<string id="task_ginek_vlip_1">
		<rus>Найти полные колбы</rus>
		<eng>Найти полные колбы</eng>
		<ukr>Знайти повні колби</ukr>
	</string>
	<string id="task_ginek_vlip_2">
		<rus>Принести колбы Гинекологу</rus>
		<eng>Принести колбы Гинекологу</eng>
		<ukr>Принести колби Гінекологу</ukr>
	</string>
	<string id="task_vuxod_atp_0">
		<rus>Поиск артефактов</rus>
		<eng>Поиск артефактов</eng>
		<ukr>Пошук артефактів</ukr>
	</string>
	<string id="task_vuxod_atp_1">
		<rus>Достать артефакты</rus>
		<eng>Достать артефакты</eng>
		<ukr>Дістати артефакти</ukr>
	</string>
	<string id="task_vuxod_atp_2">
		<rus>Принести арты Калинину</rus>
		<eng>Принести арты Калинину</eng>
		<ukr>Принести арти Калиніну</ukr>
	</string>
	<string id="task_kluk_vstrecha_0">
		<rus>Разведка территории</rus>
		<eng>Разведка территории</eng>
		<ukr>Розвідка території</ukr>
	</string>
	<string id="task_kluk_vstrecha_1">
		<rus>Провести разведку</rus>
		<eng>Провести разведку</eng>
		<ukr>Провести розвідку</ukr>
	</string>
	<string id="task_kluk_vstrecha_2">
		<rus>Поделится инфой с Клыком</rus>
		<eng>Поделится инфой с Клыком</eng>
		<ukr>Поділитися інфою з Кликом</ukr>
	</string>
	<string id="task_lukash_pechatka_0">
		<rus>Печатка Лукаша</rus>
		<eng>Печатка Лукаша</eng>
		<ukr>Печатка Лукаша</ukr>
	</string>
	<string id="task_lukash_pechatka_1">
		<rus>Найти печатку</rus>
		<eng>Найти печатку</eng>
		<ukr>Знайти печатку</ukr>
	</string>
	<string id="task_lukash_pechatka_2">
		<rus>Вернуть печатку Лукашу</rus>
		<eng>Вернуть печатку Лукашу</eng>
		<ukr>Повернути печатку Лукашу</ukr>
	</string>
	<string id="task_vitamin_reyd_0">
		<rus>Штурм Военной Лаборатории</rus>
		<eng>Штурм Военной Лаборатории</eng>
		<ukr>Штурм Військової Лаборатоії</ukr>
	</string>
	<string id="task_vitamin_reyd_1">
		<rus>Провести группу по территории Радара</rus>
		<eng>Провести группу по территории Радара</eng>
		<ukr>Провести групу по території Радару</ukr>
	</string>
	<string id="task_vitamin_reyd_2">
		<rus>Штурмовать Военную Лабораторию</rus>
		<eng>Штурмовать Военную Лабораторию</eng>
		<ukr>Штурмувати Військову Лабораторію</ukr>
	</string>
	<string id="task_pantera_fone_0">
		<rus>Телефон для Пантеры</rus>
		<eng>Телефон для Пантеры</eng>
		<ukr>Телефон для Пантери</ukr>
	</string>
	<string id="task_pantera_fone_1">
		<rus>Найти радиотелефон</rus>
		<eng>Найти радиотелефон</eng>
		<ukr>Знайти радіотелефон</ukr>
	</string>
	<string id="task_pantera_fone_2">
		<rus>Отдать телефон Пантере</rus>
		<eng>Отдать телефон Пантере</eng>
		<ukr>Віддати телефон Пантері</ukr>
	</string>
	<string id="task_pant_zadan_0">
		<rus>Диск для Пантеры</rus>
		<eng>Диск для Пантеры</eng>
		<ukr>Диск для Пантери</ukr>
	</string>
	<string id="task_pant_zadan_1">
		<rus>Найти диск</rus>
		<eng>Найти диск</eng>
		<ukr>Знайти диск</ukr>
	</string>
	<string id="task_pant_zadan_2">
		<rus>Отдать диск Пантере</rus>
		<eng>Отдать диск Пантере</eng>
		<ukr>Віддати диск Пантері</ukr>
	</string>
	<string id="task_body_pantera_0">
		<rus>Чучело псевдопса</rus>
		<eng>Чучело псевдопса</eng>
		<ukr>Опудало псевдопса</ukr>
	</string>
	<string id="task_body_pantera_1">
		<rus>Выкрасть чучело с базы на Стройплощадке</rus>
		<eng>Выкрасть чучело с базы на Стройплощадке</eng>
		<ukr>Викрасти чучело з бази на Будмайданчику</ukr>
	</string>
	<string id="task_body_pantera_2">
		<rus>Принести заказ Дембелю</rus>
		<eng>Принести заказ Дембелю</eng>
		<ukr>Принести замовлення Дембелю</ukr>
	</string>
	<string id="task_p_z_tri_0">
		<rus>Кража СКАТ-15</rus>
		<eng>Кража СКАТ-15</eng>
		<ukr>Крадіжка СКАТ-15</ukr>
	</string>
	<string id="task_p_z_tri_1">
		<rus>Найти и свистнуть СКАТ-15</rus>
		<eng>Найти и свистнуть СКАТ-15</eng>
		<ukr>Знайти і свиснути СКАТ-15</ukr>
	</string>
	<string id="task_p_z_tri_2">
		<rus>Принести заказ Пантере</rus>
		<eng>Принести заказ Пантере</eng>
		<ukr>Принести замовлення Пантері</ukr>
	</string>
	<string id="task_gologr_0">
		<rus>Сопровождение</rus>
		<eng>Сопровождение</eng>
		<ukr>Супровід</ukr>
	</string>
	<string id="task_gologr_1">
		<rus>Сопроводить Голограмму</rus>
		<eng>Сопроводить Голограмму</eng>
		<ukr>Ескортувати Голограму</ukr>
	</string>
	<string id="task_gologr_2">
		<rus>Провести Голограмму</rus>
		<eng>Провести Голограмму</eng>
		<ukr>Провести Голограму</ukr>
	</string>
	<string id="task_klenov_gol_0">
		<rus>Сопровождение, часть 2</rus>
		<eng>Сопровождение, часть 2</eng>
		<ukr>Супровід, часть 2</ukr>
	</string>
	<string id="task_klenov_gol_1">
		<rus>Сопроводить Голограмму</rus>
		<eng>Сопроводить Голограмму</eng>
		<ukr>Супроводити Голограму</ukr>
	</string>
	<string id="task_klenov_gol_2">
		<rus>Привести Голограмму к Клёнову</rus>
		<eng>Привести Голограмму к Клёнову</eng>
		<ukr>Привести Голограму до Кленова</ukr>
	</string>
	<string id="task_klenov_vse_0">
		<rus>Арты для Клёнова</rus>
		<eng>Арты для Клёнова</eng>
		<ukr>Арти для Кленова</ukr>
	</string>
	<string id="task_klenov_vse_1">
		<rus>Найти артефакты</rus>
		<eng>Найти артефакты</eng>
		<ukr>Знайти артефакти</ukr>
	</string>
	<string id="task_klenov_vse_2">
		<rus>Принести артефакты Клёнову</rus>
		<eng>Принести артефакты Клёнову</eng>
		<ukr>Привести артефакти Кленову</ukr>
	</string>
	<string id="task_esc_razvod_0">
		<rus>"Долг" Сидоровича</rus>
		<eng>"Долг" Сидоровича</eng>
		<ukr>"Борг" Сидора</ukr>
	</string>
	<string id="task_esc_razvod_1">
		<rus>Отдать долг Сидоровича</rus>
		<eng>Отдать долг Сидоровича</eng>
		<ukr>Віддати борг Сидора</ukr>
	</string>
	<string id="task_za_bablom_0">
		<rus>Проценты</rus>
		<eng>Проценты</eng>
		<ukr>Відсотки</ukr>
	</string>
	<string id="task_za_bablom_1">
		<rus>Получить у Сидора проценты</rus>
		<eng>Получить у Сидора проценты</eng>
		<ukr>Отримати у Сидора відсотки</ukr>
	</string>
	<string id="task_kolmogor_say_0">
		<rus>Помощь Колмогору</rus>
		<eng>Помощь Колмогору</eng>
		<ukr>Допомога Колмогору</ukr>
	</string>
	<string id="task_kolmogor_say_1">
		<rus>Помочь Колмогору спасти брата</rus>
		<eng>Помочь Колмогору спасти брата</eng>
		<ukr>Допомогти Колмогору врятувати брата</ukr>
	</string>
	<string id="task_sestra_start_0">
		<rus>Сестра Колмогора</rus>
		<eng>Сестра Колмогора</eng>
		<ukr>Сестра Колмогора</ukr>
	</string>
	<string id="task_sestra_start_1">
		<rus>Привести Пантеру</rus>
		<eng>Привести Пантеру</eng>
		<ukr>Привести Пантеру</ukr>
	</string>
	<string id="task_village_shtab_0">
		<rus>Штаб карателей</rus>
		<eng>Штаб карателей</eng>
		<ukr>Штаб карателів</ukr>
	</string>
	<string id="task_village_shtab_1">
		<rus>Захватить штаб карателей</rus>
		<eng>Захватить штаб карателей</eng>
		<ukr>Захопити штаб карателів</ukr>
	</string>
	<string id="task_kolm_obsledov_0">
		<rus>Осмотр деревни</rus>
		<eng>Осмотр деревни</eng>
		<ukr>Огляд селища</ukr>
	</string>
	<string id="task_kolm_obsledov_1">
		<rus>Осмотреть деревню</rus>
		<eng>Осмотреть деревню</eng>
		<ukr>Оглянути село</ukr>
	</string>
	<string id="task_kolm_obsledov_2">
		<rus>Поговорить с Колмогором</rus>
		<eng>Поговорить с Колмогором</eng>
		<ukr>Поговорити з Колмогором</ukr>
	</string>
	<string id="task_derevny_zashita_0">
		<rus>Защита деревни</rus>
		<eng>Защита деревни</eng>
		<ukr>Захист селища</ukr>
	</string>
	<string id="task_derevny_zashita_1">
		<rus>Защитить деревню</rus>
		<eng>Защитить деревню</eng>
		<ukr>Захистити село</ukr>
	</string>
	<string id="task_derevny_zashita_2">
		<rus>Поговорить с Колмогором</rus>
		<eng>Поговорить с Колмогором</eng>
		<ukr>Поговорити з Колмогором</ukr>
	</string>
	<string id="task_klenov_antena_0">
		<rus>Пси-антенна</rus>
		<eng>Пси-антенна</eng>
		<ukr>Псі-антена</ukr>
	</string>
	<string id="task_klenov_antena_1">
		<rus>Найти и забрать пси-антенну</rus>
		<eng>Найти и забрать пси-антенну</eng>
		<ukr>Знайти і забрати псі-антену</ukr>
	</string>
	<string id="task_klenov_antena_2">
		<rus>Принести антенну Клёнову</rus>
		<eng>Принести антенну Клёнову</eng>
		<ukr>Принести антену Кленову</ukr>
	</string>
	<string id="task_boloto_provod_0">
		<rus>Очищение</rus>
		<eng>Очищение</eng>
		<ukr>===Очищение</ukr>
	</string>
	<string id="task_boloto_provod_1">
		<rus>Расчистить хутор от скоплений биомасс</rus>
		<eng>Расчистить хутор от скоплений биомасс</eng>
		<ukr>===Расчистить хутор от скоплений биомасс</ukr>
	</string>
	<string id="task_boloto_provod_2">
		<rus>Вернуться к Знатоку Болот</rus>
		<eng>Вернуться к Знатоку Болот</eng>
		<ukr>===Вернуться к Знатоку Болот</ukr>
	</string>
	<string id="task_zemlyk_zadanie1_0">
		<rus>Воздушная угроза</rus>
		<eng>Воздушная угроза</eng>
		<ukr>Повітряна загроза</ukr>
	</string>
	<string id="task_zemlyk_zadanie1_1">
		<rus>Обнаружить и сбить вертуху</rus>
		<eng>Обнаружить и сбить вертуху</eng>
		<ukr>Знайти і збити вертуху</ukr>
	</string>
	<string id="task_zemlyk_zadanie1_2">
		<rus>Сообщить о результате Земляку</rus>
		<eng>Сообщить о результате Земляку</eng>
		<ukr>Повідомити про результат Земляка</ukr>
	</string>
	<string id="task_black_dok_gener_0">
		<rus>Поиски Боцмана</rus>
		<eng>Поиски Боцмана</eng>
		<ukr>Пошуки Боцмана</ukr>
	</string>
	<string id="task_black_dok_gener_1">
		<rus>Разыскать бывшего торговца Боцмана</rus>
		<eng>Разыскать бывшего торговца Боцмана</eng>
		<ukr>Розшукати бувшого крамаря Боцмана</ukr>
	</string>
	<string id="task_defend_udav_0">
		<rus>Прикрытие</rus>
		<eng>Прикрытие</eng>
		<ukr>Прикриття</ukr>
	</string>
	<string id="task_defend_udav_1">
		<rus>Убить напавших бандитов и прикрыть Боцмана</rus>
		<eng>Убить напавших бандитов и прикрыть Боцмана</eng>
		<ukr>Вбити нападаючих бандитів і прикрити Боцмана</ukr>
	</string>
	<string id="task_udav_poshli_0">
		<rus>Привести Боцмана</rus>
		<eng>Привести Боцмана</eng>
		<ukr>Привести Боцмана</ukr>
	</string>
	<string id="task_udav_poshli_1">
		<rus>Довести Боцмана</rus>
		<eng>Довести Боцмана</eng>
		<ukr>Довести Боцмана</ukr>
	</string>
	<string id="task_ander_joystik_0">
		<rus>Джойстик Андерсена</rus>
		<eng>Джойстик Андерсена</eng>
		<ukr>Джойстик Андерсена</ukr>
	</string>
	<string id="task_ander_joystik_1">
		<rus>Найти джойстик</rus>
		<eng>Найти джойстик</eng>
		<ukr>Знайти джойстик</ukr>
	</string>
	<string id="task_ander_joystik_2">
		<rus>Принести джойстик Андерсену</rus>
		<eng>Принести джойстик Андерсену</eng>
		<ukr>Принести джойстик Андерсену</ukr>
	</string>
	<string id="task_udav_pabota_0">
		<rus>Отключение пси-антенн</rus>
		<eng>Отключение пси-антенн</eng>
		<ukr>Відключення псі-антен</ukr>
	</string>
	<string id="task_udav_pabota_1">
		<rus>Отключить пси-антенны</rus>
		<eng>Отключить пси-антенны</eng>
		<ukr>Відключити псі-антени</ukr>
	</string>
	<string id="task_priz_shturm_0">
		<rus>Освобождение Пантеры</rus>
		<eng>Освобождение Пантеры</eng>
		<ukr>Звільнення Пантери</ukr>
	</string>
	<string id="task_priz_shturm_1">
		<rus>Освободить Пантеру</rus>
		<eng>Освободить Пантеру</eng>
		<ukr>Звільнити Пантеру</ukr>
	</string>
	<string id="task_black_vstrecha_0">
		<rus>Секретное досье</rus>
		<eng>Секретное досье</eng>
		<ukr>Секретне досьє</ukr>
	</string>
	<string id="task_black_vstrecha_1">
		<rus>Забрать досье</rus>
		<eng>Забрать досье</eng>
		<ukr>Забрати досьє</ukr>
	</string>
	<string id="task_peshera_nz_0">
		<rus>Скрытая пещера</rus>
		<eng>Скрытая пещера</eng>
		<ukr>Прихована печера</ukr>
	</string>
	<string id="task_peshera_nz_1">
		<rus>Обнаружить пещеру</rus>
		<eng>Обнаружить пещеру</eng>
		<ukr>Знайти печеру</ukr>
	</string>
	<string id="task_kl_na_walk_0">
		<rus>Арты Клёнова</rus>
		<eng>Арты Клёнова</eng>
		<ukr>Арти Кленова</ukr>
	</string>
	<string id="task_kl_na_walk_1">
		<rus>Забрать артефакты у Клёнова</rus>
		<eng>Забрать артефакты у Клёнова</eng>
		<ukr>Забрати артефакти у Кленова</ukr>
	</string>
	<string id="task_muha_kukl_0">
		<rus>Кукла для Мухи</rus>
		<eng>Кукла для Мухи</eng>
		<ukr>Лялька для Мухи</ukr>
	</string>
	<string id="task_muha_kukl_1">
		<rus>Найти старую куклу</rus>
		<eng>Найти старую куклу</eng>
		<ukr>Знайти стару ляльку</ukr>
	</string>
	<string id="task_muha_kukl_2">
		<rus>Принести куклу Мухе</rus>
		<eng>Принести куклу Мухе</eng>
		<ukr>Принести ляльку Мусі</ukr>
	</string>
	<string id="task_voronin_samopisez_0">
		<rus>Бортовой самописец</rus>
		<eng>Бортовой самописец</eng>
		<ukr>Бортовий самописець</ukr>
	</string>
	<string id="task_voronin_samopisez_1">
		<rus>Найти упавший вертолёт</rus>
		<eng>Найти упавший вертолёт</eng>
		<ukr>Знайти упавший вертоліт</ukr>
	</string>
	<string id="task_voronin_samopisez_2">
		<rus>Принести самописец Воронину</rus>
		<eng>Принести самописец Воронину</eng>
		<ukr>Принести самописець Вороніну</ukr>
	</string>
	<string id="task_vkluchit_generator_0">
		<rus>Запуск генератора</rus>
		<eng>Запуск генератора</eng>
		<ukr>Запуск генератора</ukr>
	</string>
	<string id="task_vkluchit_generator_1">
		<rus>Запустить третий генератор</rus>
		<eng>Запустить третий генератор</eng>
		<ukr>Запустити третій генератор</ukr>
	</string>
	<string id="task_solv_say_0">
		<rus>Отключение генераторов помех</rus>
		<eng>Отключение генераторов помех</eng>
		<ukr>Відключення генераторів перешкод</ukr>
	</string>
	<string id="task_solv_say_1">
		<rus>Отключить генераторы помех</rus>
		<eng>Отключить генераторы помех</eng>
		<ukr>Відключити генератори перешкод</ukr>
	</string>
	<string id="task_solv_say_2">
		<rus>Принести приборы Андерсену</rus>
		<eng>Принести приборы Андерсену</eng>
		<ukr>Принести прилади Андерсену</ukr>
	</string>
	<string id="task_kluk_ch2_0">
		<rus>Позиция для наблюдения</rus>
		<eng>Позиция для наблюдения</eng>
		<ukr>Позиція для спостереження</ukr>
	</string>
	<string id="task_kluk_ch2_1">
		<rus>Занять позицию, указанную Клыком</rus>
		<eng>Занять позицию, указанную Клыком</eng>
		<ukr>Зайняти позицію, вказану Кликом</ukr>
	</string>
	<string id="task_neud_pomozch_0">
		<rus>Помощь Клыку</rus>
		<eng>Помощь Клыку</eng>
		<ukr>Допомога Клику</ukr>
	</string>
	<string id="task_neud_pomozch_1">
		<rus>Вернуться и помочь Клыку</rus>
		<eng>Вернуться и помочь Клыку</eng>
		<ukr>Повернутися і допомогти Клику</ukr>
	</string>
	<string id="task_podval_sarkofag_0">
		<rus>Встреча с Молнией</rus>
		<eng>Встреча с Молнией</eng>
		<ukr>Зустріч з Блискавкою</ukr>
	</string>
	<string id="task_podval_sarkofag_1">
		<rus>Найти Молнию</rus>
		<eng>Найти Молнию</eng>
		<ukr>Знайти Блискавку</ukr>
	</string>
	<string id="task_podval_lima_0">
		<rus>Странник</rus>
		<eng>Странник</eng>
		<ukr>Мандрівник</ukr>
	</string>
	<string id="task_podval_lima_1">
		<rus>Найти странника в Лиманске</rus>
		<eng>Найти странника в Лиманске</eng>
		<ukr>Знайти мандрівника в Лиманську</ukr>
	</string>
	<string id="task_odnonog_first_0">
		<rus>Телепорт в Саркофаге</rus>
		<eng>Телепорт в Саркофаге</eng>
		<ukr>Телепорт у Саркофазі</ukr>
	</string>
	<string id="task_odnonog_first_1">
		<rus>Найти телепорт в Саркофаге</rus>
		<eng>Найти телепорт в Саркофаге</eng>
		<ukr>Знайти телепорт у Саркофагу</ukr>
	</string>
	<string id="task_odnonog_foto_0">
		<rus>Фото "Монолита"</rus>
		<eng>Фото "Монолита"</eng>
		<ukr>Фото "Моноліту"</ukr>
	</string>
	<string id="task_odnonog_foto_1">
		<rus>Сделать фото "Монолита"</rus>
		<eng>Сделать фото "Монолита"</eng>
		<ukr>Зробити фото "Моноліту"</ukr>
	</string>
	<string id="task_odnonog_foto_2">
		<rus>Принести фото Максимилиану</rus>
		<eng>Принести фото Максимилиану</eng>
		<ukr>Принести фото Максиміліану</ukr>
	</string>
	<string id="task_mesto_v_bunkere_0">
		<rus>Засада</rus>
		<eng>Засада</eng>
		<ukr>Засідка</ukr>
	</string>
	<string id="task_mesto_v_bunkere_1">
		<rus>Занять позицию и открыть дверь</rus>
		<eng>Занять позицию и открыть дверь</eng>
		<ukr>Зайняти позицію і відкрити двері</ukr>
	</string>
	<string id="task_radist_zhiv_0">
		<rus>Спасение Радиста</rus>
		<eng>Спасение Радиста</eng>
		<ukr>Порятунок Радиста</ukr>
	</string>
	<string id="task_radist_zhiv_1">
		<rus>Не дать погибнуть Радисту</rus>
		<eng>Не дать погибнуть Радисту</eng>
		<ukr>Не дозволити загинути Радисту</ukr>
	</string>
	<string id="task_taynik_radista_0">
		<rus>Тайник Радиста</rus>
		<eng>Тайник Радиста</eng>
		<ukr>Схованка Радиста</ukr>
	</string>
	<string id="task_taynik_radista_1">
		<rus>Найти и осмотреть тайник Радиста</rus>
		<eng>Найти и осмотреть тайник Радиста</eng>
		<ukr>Знайти і оглянути схованку Радиста</ukr>
	</string>
	<string id="task_otkrut_seif_sadik_0">
		<rus>Сокрытое в сейфе</rus>
		<eng>Сокрытое в сейфе</eng>
		<ukr>Приховане у сейфі</ukr>
	</string>
	<string id="task_otkrut_seif_sadik_1">
		<rus>Открыть сейф и уберечь Радиста</rus>
		<eng>Открыть сейф и уберечь Радиста</eng>
		<ukr>Відкрити сейф і зберегти Радиста</ukr>
	</string>
	<string id="task_lesnik_say_0">
		<rus>Снайперская дуэль</rus>
		<eng>Снайперская дуэль</eng>
		<ukr>Снайперська дуель</ukr>
	</string>
	<string id="task_lesnik_say_1">
		<rus>Ликвидировать снайпера</rus>
		<eng>Ликвидировать снайпера</eng>
		<ukr>===Знищити снайпера</ukr>
	</string>
	<string id="task_izomorf_dial_0">
		<rus>Фото для Клёнова</rus>
		<eng>Фото для Клёнова</eng>
		<ukr>Фото для Кленова</ukr>
	</string>
	<string id="task_izomorf_dial_1">
		<rus>Сделать две фотографии</rus>
		<eng>Сделать две фотографии</eng>
		<ukr>Зробити дві фотографії</ukr>
	</string>
	<string id="task_izomorf_dial_2">
		<rus>Принести фотографии Клёнову</rus>
		<eng>Принести фотографии Клёнову</eng>
		<ukr>Принести фотографії Кленову</ukr>
	</string>
	<string id="task_kuzy_artmodifik_0">
		<rus>Компромат</rus>
		<eng>Компромат</eng>
		<ukr>Компромат</ukr>
	</string>
	<string id="task_kuzy_artmodifik_1">
		<rus>Принести кейс с документами</rus>
		<eng>Принести кейс с документами</eng>
		<ukr>Принести кейс з документами</ukr>
	</string>
	<string id="task_kuzy_artmodifik_2">
		<rus>Отнести кейс Кузнецову</rus>
		<eng>Отнести кейс Кузнецову</eng>
		<ukr>Принести кейс Кузнєцову</ukr>
	</string>
	<string id="task_dovesti_muzhika_0">
		<rus>Помощь Черномору</rus>
		<eng>Помощь Черномору</eng>
		<ukr>Допомога Чорномору</ukr>
	</string>
	<string id="task_dovesti_muzhika_1">
		<rus>Довести Черномора до стоянки сталкеров</rus>
		<eng>Довести Черномора до стоянки сталкеров</eng>
		<ukr>Довести Чорномора до стоянки сталкерів</ukr>
	</string>
	<string id="task_plot_dialog_0">
		<rus>Хабар сталкера</rus>
		<eng>Хабар сталкера</eng>
		<ukr>Хабар сталкера</ukr>
	</string>
	<string id="task_plot_dialog_1">
		<rus>Найти плоть на Свалке</rus>
		<eng>Найти плоть на Свалке</eng>
		<ukr>Знайти плоть на Звалищі</ukr>
	</string>
	<string id="task_plot_dialog_2">
		<rus>Принести пожитки сталкеру</rus>
		<eng>Принести пожитки сталкеру</eng>
		<ukr>Принести пожитки сталкеру</ukr>
	</string>
	<string id="task_f_after_deaf_0">
		<rus>Убийца Пантеры</rus>
		<eng>Убийца Пантеры</eng>
		<ukr>Вбивця Пантери</ukr>
	</string>
	<string id="task_f_after_deaf_1">
		<rus>Найти убийцу Пантеры</rus>
		<eng>Найти убийцу Пантеры</eng>
		<ukr>Знайти вбивцю Пантери</ukr>
	</string>
	<string id="task_as_ubiysa_0">
		<rus>Чужак</rus>
		<eng>Чужак</eng>
		<ukr>Чужак</ukr>
	</string>
	<string id="task_as_ubiysa_1">
		<rus>Найти чужака на базе Свободы</rus>
		<eng>Найти чужака на базе Свободы</eng>
		<ukr>Знайти чужака на базе Волі</ukr>
	</string>
	<string id="task_kvest_vstrecha_0">
		<rus>Подслушивание</rus>
		<eng>Подслушивание</eng>
		<ukr>Підслуховування</ukr>
	</string>
	<string id="task_kvest_vstrecha_1">
		<rus>Подслушать разговор</rus>
		<eng>Подслушать разговор</eng>
		<ukr>Підслухати розмову</ukr>
	</string>
	<string id="task_kvest_saxar_telep_0">
		<rus>Телепорт Сахарова</rus>
		<eng>Телепорт Сахарова</eng>
		<ukr>Телепорт Сахарова</ukr>
	</string>
	<string id="task_kvest_saxar_telep_1">
		<rus>Найти телепорт и воспользоваться им</rus>
		<eng>Найти телепорт и воспользоваться им</eng>
		<ukr>Знайти телепорт і скористатися ним</ukr>
	</string>
	<string id="task_port_na_mg_0">
		<rus>Портал в Лиманске</rus>
		<eng>Портал в Лиманске</eng>
		<ukr>Портал у Лиманську</ukr>
	</string>
	<string id="task_port_na_mg_1">
		<rus>Найти и активировать портал</rus>
		<eng>Найти и активировать портал</eng>
		<ukr>Знайти і активувати портал</ukr>
	</string>
	<string id="task_starsh_say_0">
		<rus>Ограбление бандитов</rus>
		<eng>Ограбление бандитов</eng>
		<ukr>Пограбунок бандитів</ukr>
	</string>
	<string id="task_starsh_say_1">
		<rus>Добыть провиант и снаряжение</rus>
		<eng>Добыть провиант и снаряжение</eng>
		<ukr>Здобути провіант і спорядження</ukr>
	</string>
	<string id="task_starsh_say_2">
		<rus>Принести еду и оружие</rus>
		<eng>Принести еду и оружие</eng>
		<ukr>Принести їжу і зброю</ukr>
	</string>
	<string id="task_dci_kontrik_0">
		<rus>Неожиданная встреча</rus>
		<eng>Неожиданная встреча</eng>
		<ukr>Несподівана зустріч</ukr>
	</string>
	<string id="task_dci_kontrik_1">
		<rus>Найти и защитить, если потребуется, контролёра</rus>
		<eng>Найти и защитить, если потребуется, контролёра</eng>
		<ukr>Знайти і захистити, якщо потрібно, контролера</ukr>
	</string>
	<string id="task_uhod_iz_mg_0">
		<rus>Побег из Мёртвого Города</rus>
		<eng>Побег из Мёртвого Города</eng>
		<ukr>Втеча з Мертвого Міста</ukr>
	</string>
	<string id="task_uhod_iz_mg_1">
		<rus>Найти тайник Нормана</rus>
		<eng>Найти тайник Нормана</eng>
		<ukr>Знайти схованку Нормана</ukr>
	</string>
	<string id="task_uhod_iz_mg_2">
		<rus>Выбраться из Мёртвого Города</rus>
		<eng>Выбраться из Мёртвого Города</eng>
		<ukr>Вибратися з Мертвого Міста</ukr>
	</string>
	<string id="task_agro_tainik_norman_0">
		<rus>Тайник на Агропроме</rus>
		<eng>Тайник на Агропроме</eng>
		<ukr>Схованка на Агропромі</ukr>
	</string>
	<string id="task_agro_tainik_norman_1">
		<rus>Найти тайник на Агропроме</rus>
		<eng>Найти тайник на Агропроме</eng>
		<ukr>Знайти схованку на Агропромі</ukr>
	</string>
	<string id="task_spasty_doka_0">
		<rus>Освобождение</rus>
		<eng>Освобождение</eng>
		<ukr>Звільнення</ukr>
	</string>
	<string id="task_spasty_doka_1">
		<rus>Спасти Доктора</rus>
		<eng>Спасти Доктора</eng>
		<ukr>Врятувати Доктора</ukr>
	</string>
	<string id="task_hand_zombie_0">
		<rus>Ходячие мертвецы</rus>
		<eng>Ходячие мертвецы</eng>
		<ukr>Ходячі мертвяки</ukr>
	</string>
	<string id="task_hand_zombie_1">
		<rus>Собрать 40 рук зомби</rus>
		<eng>Собрать 40 рук зомби</eng>
		<ukr>Принести 40 Рук Зомбі</ukr>
	</string>
	<string id="task_hand_zombie_2">
		<rus>Принести руки зомби Акиму</rus>
		<eng>Принести руки зомби Акиму</eng>
		<ukr>Принести руки зомбі Акиму</ukr>
	</string>
	<string id="task_doc_0">
		<rus>Старые документы: часть 1</rus>
		<eng>Старые документы: часть 1</eng>
		<ukr>Старі документи: частина 1</ukr>
	</string>
	<string id="task_doc_1">
		<rus>Найти старые документы</rus>
		<eng>Найти старые документы</eng>
		<ukr>Знайти старі документи</ukr>
	</string>
	<string id="task_doc_2">
		<rus>Принести документы Акиму</rus>
		<eng>Принести документы Акиму</eng>
		<ukr>Принести документи Акиму</ukr>
	</string>
	<string id="task_doc_2_0">
		<rus>Старые документы: часть 2</rus>
		<eng>Старые документы: часть 2</eng>
		<ukr>Старі документи: частина 2</ukr>
	</string>
	<string id="task_doc_2_1">
		<rus>Найти старые документы</rus>
		<eng>Найти старые документы</eng>
		<ukr>Знайти старі документи</ukr>
	</string>
	<string id="task_doc_2_2">
		<rus>Принести документы Акиму</rus>
		<eng>Принести документы Акиму</eng>
		<ukr>Принести документи Акиму</ukr>
	</string>
	<string id="task_doc_3_0">
		<rus>Старые документы: часть 3</rus>
		<eng>Старые документы: часть 3</eng>
		<ukr>Старі документи: частина 3</ukr>
	</string>
	<string id="task_doc_3_1">
		<rus>Найти старые документы</rus>
		<eng>Найти старые документы</eng>
		<ukr>Знайти старі документи</ukr>
	</string>
	<string id="task_doc_3_2">
		<rus>Принести документы Акиму</rus>
		<eng>Принести документы Акиму</eng>
		<ukr>Принести документи Акиму</ukr>
	</string>
	<string id="task_doc_4_0">
		<rus>Старые документы: часть 4</rus>
		<eng>Старые документы: часть 4</eng>
		<ukr>Старі документи: частина 4</ukr>
	</string>
	<string id="task_doc_4_1">
		<rus>Найти старые документы и ПДА</rus>
		<eng>Найти старые документы и ПДА</eng>
		<ukr>Знайти старі документи і КПК</ukr>
	</string>
	<string id="task_doc_4_2">
		<rus>Отнести найденное Акиму</rus>
		<eng>Отнести найденное Акиму</eng>
		<ukr>Віднести знайдене Акиму</ukr>
	</string>
	<string id="task_doc_tvar_0">
		<rus>"От каждой твари по части"</rus>
		<eng>"От каждой твари по части"</eng>
		<ukr>"Від кожної тварі по частині"</ukr>
	</string>
	<string id="task_doc_tvar_1">
		<rus>Найти "от каждой твари по части"</rus>
		<eng>Найти "от каждой твари по части"</eng>
		<ukr>Знайти "від кожної тварі по частині"</ukr>
	</string>
	<string id="task_doc_tvar_2">
		<rus>Отдать части монстров Акиму</rus>
		<eng>Отдать части монстров Акиму</eng>
		<ukr>Віддати частини монстрів Акиму</ukr>
	</string>
	<string id="task_qeast_q_1_0">
		<rus>Артефакты для Креста</rus>
		<eng>Артефакты для Креста</eng>
		<ukr>Артефакти для Хреста</ukr>
	</string>
	<string id="task_qeast_q_1_1">
		<rus>Найти 15 артефактов</rus>
		<eng>Найти 15 артефактов</eng>
		<ukr>Найти 15 артефактів</ukr>
	</string>
	<string id="task_qeast_q_1_2">
		<rus>Принести арты Кресту</rus>
		<eng>Принести арты Кресту</eng>
		<ukr>Принести арти Хресту</ukr>
	</string>
	<string id="task_qeast_b_0">
		<rus>Аномальные «Бизоны»</rus>
		<eng>Аномальные «Бизоны»</eng>
		<ukr>Аномальні «Бізони»</ukr>
	</string>
	<string id="task_qeast_b_1">
		<rus>Найти 6 аномальных «Бизонов»</rus>
		<eng>Найти 6 аномальных «Бизонов»</eng>
		<ukr>Знайти 6 аномальних «Бізонів»</ukr>
	</string>
	<string id="task_qeast_b_2">
		<rus>Принести пушки Кресту</rus>
		<eng>Принести пушки Кресту</eng>
		<ukr>Принести пушки Хресту</ukr>
	</string>
	<string id="task_teleporter_0">
		<rus>Ручной телепорт</rus>
		<eng>Ручной телепорт</eng>
		<ukr>Ручний телепорт</ukr>
	</string>
	<string id="task_teleporter_1">
		<rus>Отыскать военного с ручным телепортом</rus>
		<eng>Отыскать военного с ручным телепортом</eng>
		<ukr>Відшукати військового з ручним телепортом</ukr>
	</string>
	<string id="task_teleporter_2">
		<rus>Принести телепорт Кресту</rus>
		<eng>Принести телепорт Кресту</eng>
		<ukr>Принести телепорт Хресту</ukr>
	</string>
	<string id="task_flamethrower_quest_task_0">
		<rus>Починка огнемёта</rus>
		<eng>Починка огнемёта</eng>
		<ukr>Ремонт вогнемета</ukr>
	</string>
	<string id="task_flamethrower_quest_task_1">
		<rus>Найти артефакт "Огненный шар"</rus>
		<eng>Найти артефакт "Огненный шар"</eng>
		<ukr>Знайти артефакт "Вогняна куля"</ukr>
	</string>
	<string id="task_flamethrower_quest_task_2">
		<rus>Найти трубки</rus>
		<eng>Найти трубки</eng>
		<ukr>Знайти трубки</ukr>
	</string>
	<string id="task_flamethrower_quest_task_3">
		<rus>Найти манометр (датчик давления)</rus>
		<eng>Найти манометр (датчик давления)</eng>
		<ukr>Знайти манометр (датчик тиску)</ukr>
	</string>
	<string id="task_flamethrower_quest_task_4">
		<rus>Найти горелку</rus>
		<eng>Найти горелку</eng>
		<ukr>Знайти пальник</ukr>
	</string>
	<string id="task_flamethrower_quest_task_5">
		<rus>Найти 10 бутылок водки</rus>
		<eng>Найти 10 бутылок водки</eng>
		<ukr>Знайти 10 пляшок горілки</ukr>
	</string>
	<string id="task_flamethrower_quest_task_6">
		<rus>Отнести найденное Шурупу</rus>
		<eng>Отнести найденное Шурупу</eng>
		<ukr>Віднести знайдене Шурупу</ukr>
	</string>
</string_table>
